inception/cli/__init__.py
inception/cli/commands/__init__.py
inception/cli/commands/project.py
inception/cli/main.py
inception/cli/utils.py
inception_cli-0.1.1.dist-info/LICENSE
inception_cli-0.1.1.dist-info/METADATA
inception_cli-0.1.1.dist-info/WHEEL
inception_cli-0.1.1.dist-info/entry_points.txt
inception_cli-0.1.1.dist-info/RECORD
