Metadata-Version: 2.1
Name: inception-cli
Version: 0.1.1
Summary: INCEpTION command line tool
Home-page: https://github.com/inception-project/inception-cli
License: Apache-2.0
Keywords: INCEpTION
Author: The INCEpTION Project
Maintainer: Richard Eckart de Castilho
Requires-Python: >=3.8,<4.0
Classifier: License :: OSI Approved :: Apache Software License
Classifier: Programming Language :: Python :: 3
Classifier: Programming Language :: Python :: 3.8
Classifier: Programming Language :: Python :: 3.9
Classifier: Programming Language :: Python :: 3.10
Classifier: Programming Language :: Python :: 3.11
Classifier: Programming Language :: Python :: 3.12
Requires-Dist: click (==8.1.7)
Requires-Dist: pycaprio (==0.3.0)
Project-URL: Repository, https://github.com/inception-project/inception-cli
